fixturemigration
