Metadata-Version: 1.1
Name: django-fixturemigration
Version: 0.7
Summary: An app to load fixtures inside a migration data step
Home-page: https://github.com/emiliosanchez/django-fixturemigration
Author: Emilio A. Sánchez
Author-email: emilio@commite.co
License: UNKNOWN
Keywords: django,migrations,fixtures
Platform: UNKNOWN
Classifier: Programming Language :: Python
Classifier: Topic :: Software Development :: Libraries :: Python Modules
Classifier: License :: OSI Approved :: MIT License
Classifier: Environment :: Web Environment
Classifier: Development Status :: 3 - Alpha
Classifier: Programming Language :: Python :: 2.6
Classifier: Programming Language :: Python :: 2.7
Classifier: Framework :: Django
Classifier: Framework :: Django :: 1.7
Classifier: Framework :: Django :: 1.8
